ses_message_definitions/__init__.py
ses_message_definitions/common_pb2.py
ses_message_definitions/compile_proto.sh
ses_message_definitions/proto/common.proto
ses_message_definitions/proto/ur10.proto
ses_message_definitions/ur10_pb2.py
ses_message_definitions-0.1.4.dist-info/WHEEL
ses_message_definitions-0.1.4.dist-info/METADATA
ses_message_definitions-0.1.4.dist-info/RECORD
