Metadata-Version: 2.1
Name: ses-message-definitions
Version: 0.1.4
Summary: protobuf message defintions for ses 
Author: Vinu ESB
Author-email: vinu.vijayakumaran_nair@reutlingen-university.de
Requires-Python: >=3.7,<4.0
Classifier: Programming Language :: Python :: 3
Classifier: Programming Language :: Python :: 3.7
Classifier: Programming Language :: Python :: 3.8
Requires-Dist: protobuf (>=3.11.3,<4.0.0)
